{
  "type": "ifp",
  "name": "LAPDAN2",
  "version": 0,
  "animations": [
    {
      "name": "LAPDAN_D",
      "bones": [
        {
          "name": "Root",
          "keyframes": 302
        },
        {
          "name": " Pelvis",
          "keyframes": 302
        },
        {
          "name": " Spine",
          "keyframes": 302
        },
        {
          "name": " Spine1",
          "keyframes": 302
        },
        {
          "name": " Neck",
          "keyframes": 302
        },
        {
          "name": " Head",
          "keyframes": 302
        },
        {
          "name": "Bip01 L Clavicle",
          "keyframes": 302
        },
        {
          "name": " L UpperArm",
          "keyframes": 302
        },
        {
          "name": " L ForeArm",
          "keyframes": 302
        },
        {
          "name": " L Hand",
          "keyframes": 302
        },
        {
          "name": " L Finger",
          "keyframes": 302
        },
        {
          "name": "L Finger01",
          "keyframes": 302
        },
        {
          "name": "Bip01 R Clavicle",
          "keyframes": 302
        },
        {
          "name": " R UpperArm",
          "keyframes": 302
        },
        {
          "name": " R ForeArm",
          "keyframes": 302
        },
        {
          "name": " R Hand",
          "keyframes": 302
        },
        {
          "name": " R Finger",
          "keyframes": 302
        },
        {
          "name": "R Finger01",
          "keyframes": 302
        },
        {
          "name": " L Thigh",
          "keyframes": 302
        },
        {
          "name": " L Calf",
          "keyframes": 302
        },
        {
          "name": " L Foot",
          "keyframes": 302
        },
        {
          "name": " L Toe0",
          "keyframes": 302
        },
        {
          "name": " R Thigh",
          "keyframes": 302
        },
        {
          "name": " R Calf",
          "keyframes": 302
        },
        {
          "name": " R Foot",
          "keyframes": 302
        },
        {
          "name": " R Toe0",
          "keyframes": 302
        }
      ]
    },
    {
      "name": "LAPDAN_P",
      "bones": [
        {
          "name": "Normal",
          "keyframes": 301
        },
        {
          "name": " Pelvis",
          "keyframes": 301
        },
        {
          "name": " Spine 1",
          "keyframes": 301
        },
        {
          "name": " Spine 2",
          "keyframes": 301
        },
        {
          "name": " Neck",
          "keyframes": 301
        },
        {
          "name": " Head",
          "keyframes": 301
        },
        {
          "name": "Bip01 L Clavicle",
          "keyframes": 301
        },
        {
          "name": " L UpperArm",
          "keyframes": 301
        },
        {
          "name": " L ForeArm",
          "keyframes": 301
        },
        {
          "name": " L Hand",
          "keyframes": 301
        },
        {
          "name": " L Finger",
          "keyframes": 301
        },
        {
          "name": "L Finger01",
          "keyframes": 301
        },
        {
          "name": "Bip01 R Clavicle",
          "keyframes": 301
        },
        {
          "name": " R UpperArm",
          "keyframes": 301
        },
        {
          "name": " R ForeArm",
          "keyframes": 301
        },
        {
          "name": " R Hand",
          "keyframes": 301
        },
        {
          "name": " R Finger",
          "keyframes": 301
        },
        {
          "name": "R Finger01",
          "keyframes": 301
        },
        {
          "name": " L Thigh",
          "keyframes": 301
        },
        {
          "name": " L Calf",
          "keyframes": 301
        },
        {
          "name": " L Foot",
          "keyframes": 301
        },
        {
          "name": " L Toe0",
          "keyframes": 301
        },
        {
          "name": " R Thigh",
          "keyframes": 301
        },
        {
          "name": " R Calf",
          "keyframes": 301
        },
        {
          "name": " R Foot",
          "keyframes": 301
        },
        {
          "name": " R Toe0",
          "keyframes": 301
        }
      ]
    }
  ]
}