{
  "type": "txd",
  "textures": [
    {
      "name": "ah_bdflwd",
      "width": 32,
      "height": 16,
      "format": "DXT1",
      "alpha": false
    },
    {
      "name": "AH_filthtiles2",
      "width": 32,
      "height": 32,
      "format": "DXT1",
      "alpha": false
    },
    {
      "name": "AH_filthtiles",
      "width": 32,
      "height": 32,
      "format": "DXT1",
      "alpha": false
    },
    {
      "name": "mp_burn_carpet3",
      "width": 64,
      "height": 64,
      "format": "DXT1",
      "alpha": false
    },
    {
      "name": "mp_burn_carpet1",
      "width": 64,
      "height": 64,
      "format": "DXT1",
      "alpha": false
    },
    {
      "name": "mp_burn_wall2",
      "width": 64,
      "height": 64,
      "format": "DXT1",
      "alpha": false
    },
    {
      "name": "mp_burn_carpet",
      "width": 64,
      "height": 64,
      "format": "DXT1",
      "alpha": false
    },
    {
      "name": "ah_FLKWIN",
      "width": 64,
      "height": 64,
      "format": "DXT1",
      "alpha": false
    },
    {
      "name": "motel_bathfloor",
      "width": 32,
      "height": 32,
      "format": "DXT1",
      "alpha": false
    },
    {
      "name": "motel_wall4",
      "width": 32,
      "height": 64,
      "format": "DXT1",
      "alpha": false
    },
    {
      "name": "motel_wall3",
      "width": 32,
      "height": 32,
      "format": "DXT1",
      "alpha": false
    },
    {
      "name": "ab_wall1b",
      "width": 64,
      "height": 64,
      "format": "DXT1",
      "alpha": false
    },
    {
      "name": "ab_wall3",
      "width": 64,
      "height": 64,
      "format": "DXT1",
      "alpha": false
    },
    {
      "name": "kitchen-wall1",
      "width": 32,
      "height": 32,
      "format": "DXT1",
      "alpha": false
    },
    {
      "name": "barbersflr1",
      "width": 32,
      "height": 32,
      "format": "DXT1",
      "alpha": false
    },
    {
      "name": "wall5b",
      "width": 32,
      "height": 64,
      "format": "DXT1",
      "alpha": false
    },
    {
      "name": "kit_windo_12",
      "width": 64,
      "height": 32,
      "format": "DXT1",
      "alpha": false
    },
    {
      "name": "ah_yelbadwall",
      "width": 64,
      "height": 64,
      "format": "DXT1",
      "alpha": false
    },
    {
      "name": "ab_wallPanel",
      "width": 64,
      "height": 64,
      "format": "DXT1",
      "alpha": false
    },
    {
      "name": "AH_cheapredcarpet",
      "width": 32,
      "height": 32,
      "format": "DXT1",
      "alpha": false
    },
    {
      "name": "ah_CRAKPLNK",
      "width": 64,
      "height": 64,
      "format": "DXT1",
      "alpha": false
    },
    {
      "name": "AH_oldwdpan",
      "width": 64,
      "height": 64,
      "format": "DXT1",
      "alpha": false
    },
    {
      "name": "ah_BADCEIL",
      "width": 64,
      "height": 64,
      "format": "DXT1",
      "alpha": false
    },
    {
      "name": "AH_bathwalls",
      "width": 32,
      "height": 32,
      "format": "DXT1",
      "alpha": false
    },
    {
      "name": "AH_walltile3",
      "width": 32,
      "height": 32,
      "format": "DXT1",
      "alpha": false
    },
    {
      "name": "mp_diner_ceilingdirt",
      "width": 64,
      "height": 64,
      "format": "DXT1",
      "alpha": false
    },
    {
      "name": "mp_burn_wall4",
      "width": 64,
      "height": 64,
      "format": "DXT1",
      "alpha": false
    },
    {
      "name": "mp_burn_wall3",
      "width": 64,
      "height": 64,
      "format": "DXT1",
      "alpha": false
    },
    {
      "name": "mp_burn_wall1",
      "width": 64,
      "height": 64,
      "format": "DXT1",
      "alpha": false
    },
    {
      "name": "mp_burn_ceiling",
      "width": 64,
      "height": 64,
      "format": "DXT1",
      "alpha": false
    },
    {
      "name": "mp_burn_carpet2",
      "width": 64,
      "height": 64,
      "format": "DXT1",
      "alpha": false
    },
    {
      "name": "AH_pelmet",
      "width": 32,
      "height": 16,
      "format": "DXT1",
      "alpha": false
    },
    {
      "name": "ah_mikebindsarse",
      "width": 32,
      "height": 32,
      "format": "DXT1",
      "alpha": false
    },
    {
      "name": "ah_curtains1",
      "width": 32,
      "height": 32,
      "format": "DXT1",
      "alpha": false
    },
    {
      "name": "ab_wood1",
      "width": 32,
      "height": 32,
      "format": "DXT1",
      "alpha": false
    }
  ]
}