{
  "type": "txd",
  "textures": [
    {
      "name": "Bdup2_TV",
      "width": 256,
      "height": 256,
      "format": "DXT1",
      "alpha": false
    },
    {
      "name": "Bdup2_wood",
      "width": 128,
      "height": 256,
      "format": "DXT1",
      "alpha": false
    },
    {
      "name": "Bdup2_CD",
      "width": 256,
      "height": 128,
      "format": "DXT1",
      "alpha": false
    },
    {
      "name": "Bdup2_amp",
      "width": 256,
      "height": 128,
      "format": "DXT1",
      "alpha": false
    },
    {
      "name": "Bdup2_speakers",
      "width": 128,
      "height": 256,
      "format": "DXT1",
      "alpha": false
    }
  ]
}