{
  "type": "txd",
  "textures": [
    {
      "name": "grn_window2_16",
      "width": 32,
      "height": 32,
      "format": "DXT1",
      "alpha": false
    },
    {
      "name": "ws_bigwooddoor",
      "width": 32,
      "height": 32,
      "format": "DXT1",
      "alpha": false
    },
    {
      "name": "ws_artgallery3",
      "width": 32,
      "height": 32,
      "format": "DXT1",
      "alpha": false
    },
    {
      "name": "ws_artgallery",
      "width": 32,
      "height": 32,
      "format": "DXT1",
      "alpha": false
    },
    {
      "name": "ws_copart3",
      "width": 32,
      "height": 32,
      "format": "DXT1",
      "alpha": false
    },
    {
      "name": "ws_copart2",
      "width": 32,
      "height": 32,
      "format": "DXT1",
      "alpha": false
    },
    {
      "name": "ws_copart1",
      "width": 32,
      "height": 32,
      "format": "DXT1",
      "alpha": false
    },
    {
      "name": "ws_concretenew_step",
      "width": 32,
      "height": 32,
      "format": "DXT1",
      "alpha": false
    },
    {
      "name": "ws_rooftarmac1",
      "width": 32,
      "height": 32,
      "format": "DXT1",
      "alpha": false
    },
    {
      "name": "ws_oldoffice2",
      "width": 32,
      "height": 32,
      "format": "DXT1",
      "alpha": false
    },
    {
      "name": "ws_oldoffice4",
      "width": 32,
      "height": 32,
      "format": "DXT1",
      "alpha": false
    },
    {
      "name": "concretenewb256",
      "width": 32,
      "height": 32,
      "format": "DXT1",
      "alpha": false
    },
    {
      "name": "desgreengrass",
      "width": 32,
      "height": 32,
      "format": "DXT1",
      "alpha": false
    },
    {
      "name": "ws_floortiles4",
      "width": 32,
      "height": 32,
      "format": "DXT1",
      "alpha": false
    },
    {
      "name": "concpanel_la",
      "width": 32,
      "height": 32,
      "format": "DXT1",
      "alpha": false
    },
    {
      "name": "banding4_64HV",
      "width": 16,
      "height": 16,
      "format": "DXT1",
      "alpha": false
    },
    {
      "name": "ws_coppersheet",
      "width": 32,
      "height": 32,
      "format": "DXT1",
      "alpha": false
    },
    {
      "name": "ws_stationfloor",
      "width": 32,
      "height": 32,
      "format": "DXT1",
      "alpha": false
    },
    {
      "name": "ws_cityhall7",
      "width": 32,
      "height": 32,
      "format": "DXT1",
      "alpha": false
    },
    {
      "name": "ws_cityhall9",
      "width": 32,
      "height": 32,
      "format": "DXT1",
      "alpha": false
    },
    {
      "name": "ws_cityhall8",
      "width": 16,
      "height": 32,
      "format": "DXT1",
      "alpha": false
    },
    {
      "name": "ws_cityhall4",
      "width": 32,
      "height": 32,
      "format": "DXT1",
      "alpha": false
    },
    {
      "name": "ws_cityhall6",
      "width": 32,
      "height": 16,
      "format": "DXT1",
      "alpha": false
    },
    {
      "name": "ws_cityhall3",
      "width": 32,
      "height": 32,
      "format": "DXT1",
      "alpha": false
    },
    {
      "name": "ws_cityhall2",
      "width": 16,
      "height": 32,
      "format": "DXT1",
      "alpha": false
    },
    {
      "name": "ws_cityhall1",
      "width": 32,
      "height": 32,
      "format": "DXT1",
      "alpha": false
    },
    {
      "name": "ws_cityhall5",
      "width": 32,
      "height": 32,
      "format": "DXT1",
      "alpha": false
    },
    {
      "name": "ws_bigblackdoor",
      "width": 32,
      "height": 32,
      "format": "DXT1",
      "alpha": false
    },
    {
      "name": "archazzy",
      "width": 32,
      "height": 16,
      "format": "DXT1",
      "alpha": false
    }
  ]
}