{
  "type": "txd",
  "textures": [
    {
      "name": "rrbt_badges",
      "width": 256,
      "height": 256,
      "format": "DXT3",
      "alpha": true
    },
    {
      "name": "rrbt_extas",
      "width": 128,
      "height": 128,
      "format": "DXT1",
      "alpha": false
    },
    {
      "name": "rrbt_rear",
      "width": 512,
      "height": 512,
      "format": "DXT1",
      "alpha": false
    },
    {
      "name": "rrbt_roof",
      "width": 512,
      "height": 512,
      "format": "DXT1",
      "alpha": false
    },
    {
      "name": "rrbt_salon",
      "width": 1024,
      "height": 1024,
      "format": "DXT1",
      "alpha": false
    },
    {
      "name": "rrbt_wdor_f",
      "width": 64,
      "height": 64,
      "format": "DXT1",
      "alpha": false
    },
    {
      "name": "rrbt_wheel",
      "width": 512,
      "height": 512,
      "format": "DXT1",
      "alpha": false
    },
    {
      "name": "rrbt_wnd",
      "width": 64,
      "height": 64,
      "format": "DXT1",
      "alpha": false
    },
    {
      "name": "rrbt_wnd_rr",
      "width": 64,
      "height": 64,
      "format": "DXT1",
      "alpha": false
    },
    {
      "name": "rrbt_wndfrl",
      "width": 64,
      "height": 64,
      "format": "DXT1",
      "alpha": false
    },
    {
      "name": "rrbt_wood",
      "width": 1024,
      "height": 1024,
      "format": "DXT1",
      "alpha": true
    },
    {
      "name": "rrbt_dashes",
      "width": 256,
      "height": 128,
      "format": "DXT1",
      "alpha": false
    },
    {
      "name": "rrbt_carbon",
      "width": 256,
      "height": 256,
      "format": "DXT1",
      "alpha": false
    },
    {
      "name": "rrbt_wad",
      "width": 128,
      "height": 128,
      "format": "DXT1",
      "alpha": false
    }
  ]
}