{
  "type": "dff",
  "version": "RenderWare 3.6.0.3 (SA)",
  "modelType": 1,
  "geometries": [
    {
      "index": 0,
      "vertices": 148,
      "triangles": 196,
      "materials": [
        {
          "color": {
            "r": 255,
            "g": 255,
            "b": 255,
            "a": 255
          },
          "texture": null
        }
      ]
    }
  ],
  "frames": 18,
  "dummies": [
    " R ForeArm01",
    " R Hand01",
    " R Finger01",
    "Root R Finger06",
    "Root R Finger09",
    "Root R Finger14",
    "Root R Finger17",
    "Root R Finger18",
    "Root R Finger19",
    "Root R Finger15",
    "Root R Finger16",
    "Root R Finger10",
    "Root R Finger13",
    "Root R Finger07",
    "Root R Finger08",
    "R Finger02",
    "Root R Finger05"
  ]
}