{
  "type": "dff",
  "version": "RenderWare 3.4.0.3 (VC on PC)",
  "modelType": 0,
  "geometries": [
    {
      "index": 0,
      "vertices": 1270,
      "triangles": 682,
      "materials": [
        {
          "color": {
            "r": 255,
            "g": 255,
            "b": 255,
            "a": 255
          },
          "texture": null
        },
        {
          "color": {
            "r": 255,
            "g": 255,
            "b": 255,
            "a": 255
          },
          "texture": null
        },
        {
          "color": {
            "r": 255,
            "g": 255,
            "b": 255,
            "a": 255
          },
          "texture": null
        },
        {
          "color": {
            "r": 255,
            "g": 255,
            "b": 255,
            "a": 255
          },
          "texture": null
        },
        {
          "color": {
            "r": 255,
            "g": 255,
            "b": 255,
            "a": 255
          },
          "texture": null
        },
        {
          "color": {
            "r": 255,
            "g": 255,
            "b": 255,
            "a": 255
          },
          "texture": null
        },
        {
          "color": {
            "r": 255,
            "g": 255,
            "b": 255,
            "a": 255
          },
          "texture": null
        },
        {
          "color": {
            "r": 255,
            "g": 255,
            "b": 255,
            "a": 255
          },
          "texture": null
        },
        {
          "color": {
            "r": 255,
            "g": 255,
            "b": 255,
            "a": 255
          },
          "texture": null
        }
      ]
    }
  ],
  "frames": 26,
  "dummies": [
    "odn_majestic2x_nt",
    "omni_nt51",
    "omni_nt50",
    "omni_nt48",
    "omni_nt41",
    "omni_nt40",
    "omni_nt39",
    "omni_nt38",
    "omni_nt37",
    "omni_nt36",
    "omni_nt28",
    "omni_nt27",
    "omni_nt26",
    "omni_nt25",
    "omni_nt24",
    "omni_nt23",
    "omni_nt22",
    "omni_nt21",
    "omni_nt20",
    "omni_nt19",
    "omni_nt18",
    "omni_nt17",
    "omni_nt16",
    "omni_nt15",
    "Collision_Mesh01",
    "omni_nt14"
  ]
}