{
  "type": "txd",
  "textures": [
    {
      "name": "metalblack1",
      "width": 128,
      "height": 128,
      "format": "DXT1",
      "alpha": false
    },
    {
      "name": "metalblack1-2",
      "width": 128,
      "height": 128,
      "format": "DXT1",
      "alpha": false
    },
    {
      "name": "bacteria7-256x256",
      "width": 256,
      "height": 256,
      "format": "DXT1",
      "alpha": false
    },
    {
      "name": "metal10",
      "width": 128,
      "height": 128,
      "format": "DXT1",
      "alpha": false
    },
    {
      "name": "alienliquid1",
      "width": 128,
      "height": 128,
      "format": "DXT1",
      "alpha": false
    }
  ]
}